mindflow/__init__.py
mindflow/main.py
mindflow/settings.py
mindflow/cli/__init__.py
mindflow/cli/new_click_cli/__init__.py
mindflow/cli/new_click_cli/cli_main.py
mindflow/cli/new_click_cli/util.py
mindflow/cli/new_click_cli/commands/__init__.py
mindflow/cli/new_click_cli/commands/chat.py
mindflow/cli/new_click_cli/commands/config.py
mindflow/cli/new_click_cli/commands/delete.py
mindflow/cli/new_click_cli/commands/index.py
mindflow/cli/new_click_cli/commands/inspect.py
mindflow/cli/new_click_cli/commands/login.py
mindflow/cli/new_click_cli/commands/query.py
mindflow/core/__init__.py
mindflow/core/chat.py
mindflow/core/delete.py
mindflow/core/index.py
mindflow/core/inspect.py
mindflow/core/login.py
mindflow/core/query.py
mindflow/db/__init__.py
mindflow/db/controller.py
mindflow/db/utils.py
mindflow/db/db/__init__.py
mindflow/db/db/database.py
mindflow/db/db/json.py
mindflow/db/db/neo4j.py
mindflow/db/db/static.py
mindflow/db/objects/__init__.py
mindflow/db/objects/base.py
mindflow/db/objects/document.py
mindflow/db/objects/mindflow_model.py
mindflow/db/objects/model.py
mindflow/db/objects/service.py
mindflow/db/objects/static_definition/__init__.py
mindflow/db/objects/static_definition/document.py
mindflow/db/objects/static_definition/mind_flow_model.py
mindflow/db/objects/static_definition/model.py
mindflow/db/objects/static_definition/model_type.py
mindflow/db/objects/static_definition/object.py
mindflow/db/objects/static_definition/service.py
mindflow/resolving/__init__.py
mindflow/resolving/resolve.py
mindflow/resolving/resolvers/__init__.py
mindflow/resolving/resolvers/base_resolver.py
mindflow/resolving/resolvers/file_resolver.py
mindflow/utils/__init__.py
mindflow/utils/enum.py
mindflow/utils/prompt_builders.py
mindflow/utils/prompts.py
mindflow/utils/response.py
mindflow/utils/files/__init__.py
mindflow/utils/files/extract.py
mindflow/utils/files/git.py
mindflow/utils/files/utf8.py
mindflow-0.3.10.dist-info/METADATA
mindflow-0.3.10.dist-info/WHEEL
mindflow-0.3.10.dist-info/entry_points.txt
mindflow-0.3.10.dist-info/top_level.txt
mindflow-0.3.10.dist-info/RECORD
