Metadata-Version: 2.1
Name: mindflow
Version: 0.3.10
Summary: AI-powered search engine for your code!
Requires-Python: >=3.7.1
Requires-Dist: alive-progress
Requires-Dist: click
Requires-Dist: numpy
Requires-Dist: openai (==0.27.0)
Requires-Dist: pytest
Requires-Dist: scikit-learn
Requires-Dist: tqdm
Requires-Dist: traitlets
